FixObsImgDpy/__init__.py
FixObsImgDpy-0.1.0.dist-info/METADATA
FixObsImgDpy-0.1.0.dist-info/WHEEL
FixObsImgDpy-0.1.0.dist-info/entry_points.txt
FixObsImgDpy-0.1.0.dist-info/top_level.txt
FixObsImgDpy-0.1.0.dist-info/zip-safe
FixObsImgDpy-0.1.0.dist-info/RECORD
