Metadata-Version: 2.1
Name: FixObsImgDpy
Version: 0.1.0
Summary: Fix "<img>" display issues in obsidian 
Home-page: https://github.com/TheHonestDearmer1
Author: TheHonestDreamer
Author-email: 2356371636@qq.com
License: MIT
Classifier: Intended Audience :: Developers
Classifier: Programming Language :: Python
Classifier: Programming Language :: Python :: 3
Classifier: Programming Language :: Python :: 3.4
Classifier: Programming Language :: Python :: 3.5
Classifier: Programming Language :: Python :: 3.6
Classifier: Programming Language :: Python
Classifier: Programming Language :: Python :: 3.7
Classifier: Programming Language :: Python :: 3.8
Classifier: Programming Language :: Python :: 3.9
Classifier: Programming Language :: Python :: 3.10
Classifier: Programming Language :: Python :: 3.11
Classifier: Topic :: Software Development :: Libraries
